PairWisePython/__init__.py
PairWisePython/main.py
pairwisepython-0.0.3.dist-info/METADATA
pairwisepython-0.0.3.dist-info/WHEEL
pairwisepython-0.0.3.dist-info/licenses/LICENSE
pairwisepython-0.0.3.dist-info/RECORD
