Metadata-Version: 2.3
Name: PairWisePython
Version: 0.0.3
Summary: This library is for generating pairwise data
Author-email: Nikita <satanis70@gmail.com>
License-File: LICENSE
Classifier: License :: OSI Approved :: MIT License
Classifier: Operating System :: OS Independent
Classifier: Programming Language :: Python :: 3
Requires-Python: >=3.10.0
